polywrap_uri_resolvers/__init__.py
polywrap_uri_resolvers/errors.py
polywrap_uri_resolvers/py.typed
polywrap_uri_resolvers/resolvers/__init__.py
polywrap_uri_resolvers/resolvers/abc/__init__.py
polywrap_uri_resolvers/resolvers/abc/resolver_with_history.py
polywrap_uri_resolvers/resolvers/aggregator/__init__.py
polywrap_uri_resolvers/resolvers/aggregator/uri_resolver_aggregator.py
polywrap_uri_resolvers/resolvers/aggregator/uri_resolver_aggregator_base.py
polywrap_uri_resolvers/resolvers/cache/__init__.py
polywrap_uri_resolvers/resolvers/cache/resolution_result_cache_resolver.py
polywrap_uri_resolvers/resolvers/extensions/__init__.py
polywrap_uri_resolvers/resolvers/extensions/extendable_uri_resolver.py
polywrap_uri_resolvers/resolvers/extensions/extension_wrapper_uri_resolver.py
polywrap_uri_resolvers/resolvers/extensions/uri_resolver_extension_file_reader.py
polywrap_uri_resolvers/resolvers/legacy/__init__.py
polywrap_uri_resolvers/resolvers/legacy/base_resolver.py
polywrap_uri_resolvers/resolvers/legacy/fs_resolver.py
polywrap_uri_resolvers/resolvers/legacy/package_to_wrapper_resolver.py
polywrap_uri_resolvers/resolvers/legacy/redirect_resolver.py
polywrap_uri_resolvers/resolvers/legacy/wrapper_cache/__init__.py
polywrap_uri_resolvers/resolvers/legacy/wrapper_cache/in_memory_wrapper_cache.py
polywrap_uri_resolvers/resolvers/legacy/wrapper_cache/wrapper_cache.py
polywrap_uri_resolvers/resolvers/legacy/wrapper_cache_resolver.py
polywrap_uri_resolvers/resolvers/package/__init__.py
polywrap_uri_resolvers/resolvers/package/package_resolver.py
polywrap_uri_resolvers/resolvers/recursive/__init__.py
polywrap_uri_resolvers/resolvers/recursive/recursive_resolver.py
polywrap_uri_resolvers/resolvers/redirect/__init__.py
polywrap_uri_resolvers/resolvers/redirect/redirect_resolver.py
polywrap_uri_resolvers/resolvers/static/__init__.py
polywrap_uri_resolvers/resolvers/static/static_resolver.py
polywrap_uri_resolvers/resolvers/wrapper/__init__.py
polywrap_uri_resolvers-0.1.2.dist-info/METADATA
polywrap_uri_resolvers-0.1.2.dist-info/WHEEL
polywrap_uri_resolvers-0.1.2.dist-info/RECORD
